re_it/__init__.py
re_it/请求.py
re_it-1.1.1.0.dist-info/METADATA
re_it-1.1.1.0.dist-info/WHEEL
re_it-1.1.1.0.dist-info/top_level.txt
re_it-1.1.1.0.dist-info/RECORD
