Metadata-Version: 2.1
Name: re-it
Version: 1.1.1.0
Summary: 中文的python网络请求库！
Home-page: https://pypi.org/user/SuiBo/
Author: SuiBo
Author-email: 534047068@qq.com
License: UNKNOWN
Platform: UNKNOWN
